typetest_cli/__init__.py
typetest_cli/typetest.py
typetest_cli/text/1.txt
typetest_cli/text/10.txt
typetest_cli/text/11.txt
typetest_cli/text/12.txt
typetest_cli/text/13.txt
typetest_cli/text/14.txt
typetest_cli/text/15.txt
typetest_cli/text/16.txt
typetest_cli/text/17.txt
typetest_cli/text/18.txt
typetest_cli/text/19.txt
typetest_cli/text/2.txt
typetest_cli/text/3.txt
typetest_cli/text/4.txt
typetest_cli/text/5.txt
typetest_cli/text/6.txt
typetest_cli/text/7.txt
typetest_cli/text/8.txt
typetest_cli/text/9.txt
typetest_cli-1.2.5.dist-info/licenses/LICENSE
typetest_cli-1.2.5.dist-info/METADATA
typetest_cli-1.2.5.dist-info/WHEEL
typetest_cli-1.2.5.dist-info/entry_points.txt
typetest_cli-1.2.5.dist-info/top_level.txt
typetest_cli-1.2.5.dist-info/RECORD
