Metadata-Version: 2.4
Name: typetest-cli
Version: 1.2.5
Summary: Lightweight typing speed commandline tool
Author: Kyler
Project-URL: repository, https://github.com/senyc/typetest-cli
Keywords: speed,test,typing,typetest,typetest-cli,terminal
Classifier: Operating System :: POSIX :: Linux
Classifier: Environment :: Console
Classifier: Programming Language :: Python :: 3.8
Classifier: Programming Language :: Python :: 3.9
Classifier: Programming Language :: Python :: 3.10
Classifier: Programming Language :: Python :: 3.11
Classifier: Programming Language :: Python :: 3.12
Classifier: Programming Language :: Python :: 3.13
Requires-Python: >=3.8
License-File: LICENSE
Requires-Dist: rich
Dynamic: license-file
